ZMPY3D_PT/ZMPY3D_PT_CLI_BatchShapeScore.py
ZMPY3D_PT/ZMPY3D_PT_CLI_BatchSuperA2B.py
ZMPY3D_PT/ZMPY3D_PT_CLI_BatchZM.py
ZMPY3D_PT/ZMPY3D_PT_CLI_ShapeScore.py
ZMPY3D_PT/ZMPY3D_PT_CLI_SuperA2B.py
ZMPY3D_PT/ZMPY3D_PT_CLI_ZM.py
ZMPY3D_PT/__all__.py
ZMPY3D_PT/__init__.py
ZMPY3D_PT/cache_data/BinomialCache.pkl
ZMPY3D_PT/cache_data/LogG_CLMCache_MaxOrder06.pkl
ZMPY3D_PT/cache_data/LogG_CLMCache_MaxOrder20.pkl
ZMPY3D_PT/lib/__init__.py
ZMPY3D_PT/lib/calculate_ab_rotation_02_all_pt.py
ZMPY3D_PT/lib/calculate_ab_rotation_02_pt.py
ZMPY3D_PT/lib/calculate_bbox_moment_07_pt.py
ZMPY3D_PT/lib/calculate_bbox_moment_2_zm05_pt.py
ZMPY3D_PT/lib/calculate_box_by_grid_width.py
ZMPY3D_PT/lib/calculate_molecular_radius_04_pt.py
ZMPY3D_PT/lib/calculate_zm_by_ab_rotation01_pt.py
ZMPY3D_PT/lib/eigen_root_pt.py
ZMPY3D_PT/lib/eigen_root_pt2.py
ZMPY3D_PT/lib/fill_voxel_by_weight_density04.py
ZMPY3D_PT/lib/get_3dzd_121_descriptor_02_pt.py
ZMPY3D_PT/lib/get_bbox_moment_xyz_sample_01_pt.py
ZMPY3D_PT/lib/get_ca_distance_info_pt.py
ZMPY3D_PT/lib/get_descriptor_property.py
ZMPY3D_PT/lib/get_global_parameter02.py
ZMPY3D_PT/lib/get_mean_invariant_03_pt.py
ZMPY3D_PT/lib/get_pdb_xyz_ca02.py
ZMPY3D_PT/lib/get_residue_gaussian_density_cache02.py
ZMPY3D_PT/lib/get_residue_radius_map01.py
ZMPY3D_PT/lib/get_residue_weight_map01.py
ZMPY3D_PT/lib/get_total_residue_weight.py
ZMPY3D_PT/lib/get_transform_matrix_from_ab_list02_pt.py
ZMPY3D_PT/lib/read_file_as_string_list.py
ZMPY3D_PT/lib/set_pdb_xyz_rot_m_01.py
ZMPY3D_PT/lib/write_string_list_as_file.py
ZMPY3D_PT-0.0.3.dist-info/LICENSE
ZMPY3D_PT-0.0.3.dist-info/METADATA
ZMPY3D_PT-0.0.3.dist-info/WHEEL
ZMPY3D_PT-0.0.3.dist-info/entry_points.txt
ZMPY3D_PT-0.0.3.dist-info/top_level.txt
ZMPY3D_PT-0.0.3.dist-info/RECORD
