Metadata-Version: 2.1
Name: ZMPY3D_PT
Version: 0.0.3
Summary: ZMPY3D PyTorch version
Home-page: https://github.com/tawssie/ZMPY3D_PT
Author: Jhih Siang (Sean) Lai
Author-email: js.lai@uqconnect.edu.au, jsl035@ucsd.edu
Classifier: Programming Language :: Python :: 3
Classifier: License :: OSI Approved :: GNU General Public License v3 (GPLv3)
Classifier: Operating System :: OS Independent
Classifier: Topic :: Scientific/Engineering :: Bio-Informatics
Requires-Python: >=3.9.16
License-File: LICENSE
Requires-Dist: numpy>=1.23.5
